fmus_viz/__init__.py
fmus_viz/_version.py
fmus_viz/api/__init__.py
fmus_viz/api/basic.py
fmus_viz/api/statistical.py
fmus_viz/backends/__init__.py
fmus_viz/backends/matplotlib/__init__.py
fmus_viz/backends/matplotlib/basic.py
fmus_viz/backends/matplotlib/statistical.py
fmus_viz/backends/matplotlib/utils.py
fmus_viz/backends/plotly/__init__.py
fmus_viz/backends/plotly/basic.py
fmus_viz/backends/plotly/statistical.py
fmus_viz/backends/plotly/utils.py
fmus_viz/backends/seaborn/__init__.py
fmus_viz/backends/seaborn/basic.py
fmus_viz/backends/seaborn/statistical.py
fmus_viz/backends/seaborn/utils.py
fmus_viz/core/__init__.py
fmus_viz/core/base.py
fmus_viz/core/config.py
fmus_viz/core/registry.py
fmus_viz/core/utils.py
fmus_viz-0.1.0.dist-info/licenses/LICENSE
fmus_viz-0.1.0.dist-info/METADATA
fmus_viz-0.1.0.dist-info/WHEEL
fmus_viz-0.1.0.dist-info/top_level.txt
fmus_viz-0.1.0.dist-info/RECORD
