Metadata-Version: 2.4
Name: fmus-viz
Version: 0.1.0
Summary: A human-oriented visualization library with unified interface across multiple backends
Author-email: Yusef Ulum <yusef314159@gmail.com>
License: MIT
Project-URL: Documentation, https://fmus-viz.readthedocs.io
Project-URL: Source, https://github.com/mexyusef/fmus-viz
Project-URL: Issues, https://github.com/mexyusef/fmus-viz/issues
Classifier: Development Status :: 3 - Alpha
Classifier: Intended Audience :: Developers
Classifier: Intended Audience :: Science/Research
Classifier: Programming Language :: Python :: 3
Classifier: Programming Language :: Python :: 3.8
Classifier: Programming Language :: Python :: 3.9
Classifier: Programming Language :: Python :: 3.10
Classifier: Programming Language :: Python :: 3.11
Classifier: Topic :: Scientific/Engineering :: Visualization
Requires-Python: >=3.8
License-File: LICENSE
Requires-Dist: numpy>=1.20.0
Requires-Dist: pandas>=1.3.0
Provides-Extra: matplotlib
Requires-Dist: matplotlib>=3.5.0; extra == "matplotlib"
Provides-Extra: plotly
Requires-Dist: plotly>=5.5.0; extra == "plotly"
Provides-Extra: seaborn
Requires-Dist: seaborn>=0.11.0; extra == "seaborn"
Provides-Extra: bokeh
Requires-Dist: bokeh>=2.4.0; extra == "bokeh"
Provides-Extra: altair
Requires-Dist: altair>=4.2.0; extra == "altair"
Provides-Extra: networkx
Requires-Dist: networkx>=2.7.0; extra == "networkx"
Requires-Dist: pyvis>=0.2.0; extra == "networkx"
Provides-Extra: folium
Requires-Dist: folium>=0.12.0; extra == "folium"
Requires-Dist: geojson>=2.5.0; extra == "folium"
Provides-Extra: holoviews
Requires-Dist: holoviews>=1.14.0; extra == "holoviews"
Requires-Dist: datashader>=0.13.0; extra == "holoviews"
Provides-Extra: all
Requires-Dist: matplotlib>=3.5.0; extra == "all"
Requires-Dist: plotly>=5.5.0; extra == "all"
Requires-Dist: seaborn>=0.11.0; extra == "all"
Requires-Dist: bokeh>=2.4.0; extra == "all"
Requires-Dist: altair>=4.2.0; extra == "all"
Requires-Dist: networkx>=2.7.0; extra == "all"
Requires-Dist: pyvis>=0.2.0; extra == "all"
Requires-Dist: folium>=0.12.0; extra == "all"
Requires-Dist: geojson>=2.5.0; extra == "all"
Requires-Dist: holoviews>=1.14.0; extra == "all"
Requires-Dist: datashader>=0.13.0; extra == "all"
Provides-Extra: dev
Requires-Dist: pytest>=7.0.0; extra == "dev"
Requires-Dist: pytest-cov>=3.0.0; extra == "dev"
Requires-Dist: mypy>=0.950; extra == "dev"
Requires-Dist: black>=22.3.0; extra == "dev"
Requires-Dist: flake8>=4.0.0; extra == "dev"
Requires-Dist: isort>=5.10.0; extra == "dev"
Requires-Dist: sphinx>=4.5.0; extra == "dev"
Requires-Dist: sphinx-rtd-theme>=1.0.0; extra == "dev"
Requires-Dist: pre-commit>=2.18.0; extra == "dev"
Dynamic: license-file
